animator/__init__.py
animator-0.1.dist-info/LICENSE
animator-0.1.dist-info/METADATA
animator-0.1.dist-info/WHEEL
animator-0.1.dist-info/top_level.txt
animator-0.1.dist-info/RECORD
