Metadata-Version: 2.1
Name: animator
Version: 0.1
Summary: Animator is a terminal based animation library for python.
Home-page: https://github.com/tanishyadav/animator
Author: Tanish Yadav
Maintainer: Tanish Yadav
License: UNKNOWN
Keywords: python,animation,terminal,console,transistion
Platform: UNKNOWN
Classifier: Programming Language :: Python :: 3
Classifier: License :: OSI Approved :: GNU General Public License v3 (GPLv3)
Classifier: Operating System :: OS Independent
Classifier: Environment :: Console
Classifier: Intended Audience :: Developers
Classifier: Development Status :: 5 - Production/Stable
